hicmatrix/HiCMatrix.py
hicmatrix/__init__.py
hicmatrix/utilities.py
hicmatrix/lib/__init__.py
hicmatrix/lib/cool.py
hicmatrix/lib/ginteractions.py
hicmatrix/lib/h5.py
hicmatrix/lib/hicpro.py
hicmatrix/lib/homer.py
hicmatrix/lib/matrixFile.py
hicmatrix/lib/matrixFileHandler.py
hicmatrix/lib/scool.py
hicmatrix/test/test_HiCMatrix.py
hicmatrix/test/test_matrixFileHandler.py
HiCMatrix-17.2.dist-info/LICENSE
HiCMatrix-17.2.dist-info/METADATA
HiCMatrix-17.2.dist-info/WHEEL
HiCMatrix-17.2.dist-info/top_level.txt
HiCMatrix-17.2.dist-info/RECORD
