Metadata-Version: 2.1
Name: HiCMatrix
Version: 17.2
Summary: Helper package which implements HiCMatrix class for HiCExplorer, pyGenomeTracks and scHiCExplorer.
Author-email: "Lucille Lopez-Delisle, Joachim Wolff, Leily Rabbani, Vivek Bhardwaj, Fidel Ramirez" <lucille.delisle@epfl.ch>
Project-URL: Homepage, https://github.com/deeptools/HiCMatrix
Project-URL: Issues, https://github.com/deeptools/HiCMatrix/issues
Classifier: Intended Audience :: Science/Research
Classifier: Topic :: Scientific/Engineering :: Bio-Informatics
Requires-Python: >=3.7
License-File: LICENSE
Requires-Dist: numpy >=1.20
Requires-Dist: scipy >=1.2
Requires-Dist: tables >=3.5
Requires-Dist: pandas >=0.25
Requires-Dist: cooler >=0.8.9
Requires-Dist: intervaltree >=3.0
Requires-Dist: importlib-metadata ; python_version < "3.8"
